imuthes/textual/.git
imuthes/textual/__init__.py
imuthes/textual/README.md
imuthes/textual/screens/__init__.py
imuthes/textual/screens/input_popup.py
imuthes/textual/widgets/__init__.py
imuthes_textual-0.0.1.dist-info/METADATA
imuthes_textual-0.0.1.dist-info/WHEEL
imuthes_textual-0.0.1.dist-info/RECORD
